ayx_learn/__init__.py
ayx_learn/version.py
ayx_learn/base/__init__.py
ayx_learn/base/estimator.py
ayx_learn/base/pipeline.py
ayx_learn/base/pipeline_step.py
ayx_learn/base/strategy.py
ayx_learn/base/transformer.py
ayx_learn/base/inspection/__init__.py
ayx_learn/base/inspection/column_inspection.py
ayx_learn/base/inspection/failure.py
ayx_learn/base/inspection/force_drop.py
ayx_learn/base/inspection/inspection.py
ayx_learn/base/inspection/multi_column.py
ayx_learn/base/inspector/__init__.py
ayx_learn/base/inspector/base.py
ayx_learn/base/inspector/column_inspector.py
ayx_learn/base/inspector/column_wise_inspector.py
ayx_learn/base/inspector/combination.py
ayx_learn/base/inspector/safe_inspect.py
ayx_learn/base/inspector/typing.py
ayx_learn/classifiers/__init__.py
ayx_learn/classifiers/decision_tree_classifier.py
ayx_learn/classifiers/logistic_regression_classifier.py
ayx_learn/classifiers/random_forest_classifier.py
ayx_learn/classifiers/xgb_classifier.py
ayx_learn/evaluations/__init__.py
ayx_learn/evaluations/abs_error_plot.py
ayx_learn/evaluations/accuracy.py
ayx_learn/evaluations/adjr2.py
ayx_learn/evaluations/auc.py
ayx_learn/evaluations/base_auc.py
ayx_learn/evaluations/classification.py
ayx_learn/evaluations/classification_importance.py
ayx_learn/evaluations/confusion_matrix.py
ayx_learn/evaluations/evaluation.py
ayx_learn/evaluations/log_loss.py
ayx_learn/evaluations/m_auc.py
ayx_learn/evaluations/mae.py
ayx_learn/evaluations/mape.py
ayx_learn/evaluations/mre.py
ayx_learn/evaluations/multi_fold_evaluation.py
ayx_learn/evaluations/permutation_importance.py
ayx_learn/evaluations/predicted_vs_actual.py
ayx_learn/evaluations/r2.py
ayx_learn/evaluations/regression.py
ayx_learn/evaluations/regression_importance.py
ayx_learn/evaluations/rmse.py
ayx_learn/evaluations/roc.py
ayx_learn/evaluations/stratified_bin_sampler.py
ayx_learn/helpers/__init__.py
ayx_learn/helpers/entropy_binning.py
ayx_learn/helpers/goodman_kruskal_tau.py
ayx_learn/inspectors/__init__.py
ayx_learn-2020.2.0.dist-info/LICENSE
ayx_learn-2020.2.0.dist-info/METADATA
ayx_learn-2020.2.0.dist-info/WHEEL
ayx_learn-2020.2.0.dist-info/top_level.txt
ayx_learn-2020.2.0.dist-info/RECORD
